rdflib_appengine/__init__.py
rdflib_appengine/ndbstore.py
rdflib_appengine-1.2.0.data/data/README.rst
rdflib_appengine-1.2.0.dist-info/DESCRIPTION.rst
rdflib_appengine-1.2.0.dist-info/METADATA
rdflib_appengine-1.2.0.dist-info/metadata.json
rdflib_appengine-1.2.0.dist-info/RECORD
rdflib_appengine-1.2.0.dist-info/top_level.txt
rdflib_appengine-1.2.0.dist-info/WHEEL
