Metadata-Version: 2.0
Name: rdflib-appengine
Version: 1.2.0
Summary: Python distributible for using rdflib with NDB
Home-page: https://github.com/mr-niels-christensen/rdflib-appengine
Author: Niels Christensen
Author-email: nhc@mayacs.com
License: Apache 2.0
Keywords: semantic-web rdf rdflib google-app-engine gae ndb
Platform: UNKNOWN
Classifier: Development Status :: 4 - Beta
Classifier: Intended Audience :: Developers
Classifier: Topic :: Software Development :: Libraries
Classifier: License :: OSI Approved :: Apache Software License
Classifier: Programming Language :: Python :: 2.7
Requires-Dist: rdflib (==4.1.2)
